README.md
setup.py
absp/__init__.py
absp.egg-info/PKG-INFO
absp.egg-info/SOURCES.txt
absp.egg-info/dependency_links.txt
absp.egg-info/top_level.txt